libobj-503.data/scripts/obj
obj/disk.py
obj/find.py
obj/method.py
obj/object.py
libobj-503.dist-info/METADATA
libobj-503.dist-info/WHEEL
libobj-503.dist-info/top_level.txt
libobj-503.dist-info/zip-safe
libobj-503.dist-info/RECORD
