Metadata-Version: 2.1
Name: libobj
Version: 503
Summary: object library
Author-email: libbot <libbotx@gmail.com>
License: Public Domain
Project-URL: home, https://pypi.org/project/libobj
Project-URL: bugs, https://github.com/botlibx/libobj/issues
Project-URL: source, https://github.com/botlibx/libobj
Classifier: Development Status :: 3 - Alpha
Classifier: License :: Public Domain
Classifier: Operating System :: Unix
Classifier: Programming Language :: Python
Classifier: Topic :: Utilities
